MANIFEST.in
README.rst
setup.cfg
setup.py
TracBlockdiag.egg-info/PKG-INFO
TracBlockdiag.egg-info/SOURCES.txt
TracBlockdiag.egg-info/dependency_links.txt
TracBlockdiag.egg-info/entry_points.txt
TracBlockdiag.egg-info/requires.txt
TracBlockdiag.egg-info/top_level.txt
tracblockdiag/__init__.py
tracblockdiag/cache.py
tracblockdiag/diag.py
tracblockdiag/plugin.py