Metadata-Version: 1.0
Name: TracBlockdiag
Version: 0.2.1
Summary: Integrate blockdiag series into Trac wiki
Home-page: https://github.com/yosisa/TracBlockdiag
Author: Yoshihisa Tanaka
Author-email: yt.hisa@gmail.com
License: MIT
Keywords: trac,macro,blockdiag
Platform: UNKNOWN
Classifier: Development Status :: 4 - Beta
Classifier: Intended Audience :: System Administrators
Classifier: Programming Language :: Python
Classifier: License :: OSI Approved :: MIT License
Classifier: Framework :: Trac
Classifier: Environment :: Plugins
